sage_libs/__init__.py
sage_libs/sage_eval/__init__.py
sage_libs/sage_eval/_register.py
sage_libs/sage_eval/_version.py
sage_libs/sage_eval/judges/__init__.py
sage_libs/sage_eval/judges/faithfulness.py
sage_libs/sage_eval/judges/relevance.py
sage_libs/sage_eval/metrics/__init__.py
sage_libs/sage_eval/metrics/accuracy.py
sage_libs/sage_eval/metrics/bleu.py
sage_libs/sage_eval/metrics/f1.py
sage_libs/sage_eval/profilers/__init__.py
sage_libs/sage_eval/profilers/latency.py
sage_libs/sage_eval/profilers/throughput.py
isage_eval-0.1.0.0.dist-info/METADATA
isage_eval-0.1.0.0.dist-info/WHEEL
isage_eval-0.1.0.0.dist-info/top_level.txt
isage_eval-0.1.0.0.dist-info/RECORD
